vendy_bc/__init__.py
vendy_bc/__main__.py
vendy_bc/cli/__init__.py
vendy_bc/cli/color.py
vendy_bc/cli/dialog_creator.py
vendy_bc/cli/feature_handler.py
vendy_bc/cli/file_dialog.py
vendy_bc/cli/main.py
vendy_bc/cli/save_management.py
vendy_bc/cli/server_cli.py
vendy_bc/cli/edits/__init__.py
vendy_bc/cli/edits/aku_realm.py
vendy_bc/cli/edits/basic_items.py
vendy_bc/cli/edits/cat_editor.py
vendy_bc/cli/edits/clear_tutorial.py
vendy_bc/cli/edits/enemy_editor.py
vendy_bc/cli/edits/fixes.py
vendy_bc/cli/edits/map.py
vendy_bc/cli/edits/rare_ticket_trade.py
vendy_bc/core/__init__.py
vendy_bc/core/country_code.py
vendy_bc/core/crypto.py
vendy_bc/core/game_version.py
vendy_bc/core/locale_handler.py
vendy_bc/core/log.py
vendy_bc/core/max_value_helper.py
vendy_bc/core/theme_handler.py
vendy_bc/core/game/__init__.py
vendy_bc/core/game/localizable.py
vendy_bc/core/game/battle/__init__.py
vendy_bc/core/game/battle/battle_items.py
vendy_bc/core/game/battle/cleared_slots.py
vendy_bc/core/game/battle/enemy.py
vendy_bc/core/game/battle/slots.py
vendy_bc/core/game/catbase/__init__.py
vendy_bc/core/game/catbase/beacon_base.py
vendy_bc/core/game/catbase/cat.py
vendy_bc/core/game/catbase/drop_chara.py
vendy_bc/core/game/catbase/gambling.py
vendy_bc/core/game/catbase/gatya.py
vendy_bc/core/game/catbase/gatya_item.py
vendy_bc/core/game/catbase/item_pack.py
vendy_bc/core/game/catbase/login_bonuses.py
vendy_bc/core/game/catbase/matatabi.py
vendy_bc/core/game/catbase/medals.py
vendy_bc/core/game/catbase/mission.py
vendy_bc/core/game/catbase/my_sale.py
vendy_bc/core/game/catbase/nyanko_club.py
vendy_bc/core/game/catbase/officer_pass.py
vendy_bc/core/game/catbase/playtime.py
vendy_bc/core/game/catbase/powerup.py
vendy_bc/core/game/catbase/scheme_items.py
vendy_bc/core/game/catbase/special_skill.py
vendy_bc/core/game/catbase/stamp.py
vendy_bc/core/game/catbase/talent_orbs.py
vendy_bc/core/game/catbase/unlock_popups.py
vendy_bc/core/game/catbase/upgrade.py
vendy_bc-0.1.2.dist-info/METADATA
vendy_bc-0.1.2.dist-info/WHEEL
vendy_bc-0.1.2.dist-info/entry_points.txt
vendy_bc-0.1.2.dist-info/top_level.txt
vendy_bc-0.1.2.dist-info/RECORD
